ncbi_cds_from_protein/__init__.py
ncbi_cds_from_protein/caches.py
ncbi_cds_from_protein/entrez.py
ncbi_cds_from_protein/logger.py
ncbi_cds_from_protein/ncfp_tools.py
ncbi_cds_from_protein/sequences.py
ncbi_cds_from_protein/scripts/__init__.py
ncbi_cds_from_protein/scripts/logger.py
ncbi_cds_from_protein/scripts/ncfp.py
ncbi_cds_from_protein/scripts/parsers.py
ncfp-0.2.0.dist-info/LICENSE
ncfp-0.2.0.dist-info/METADATA
ncfp-0.2.0.dist-info/WHEEL
ncfp-0.2.0.dist-info/entry_points.txt
ncfp-0.2.0.dist-info/top_level.txt
ncfp-0.2.0.dist-info/RECORD
