Metadata-Version: 2.1
Name: ncfp
Version: 0.2.0
Summary: ncfp is a script and module that facilitates recovery of nucleotide sequences from NCBI encoding a specified set of input protein sequences
Home-page: http://widdowquinn.github.io/ncfp/
Author: Leighton Pritchard
Author-email: leighton.pritchard@hutton.ac.uk
License: MIT
Download-URL: https://github.com/widdowquinn/ncfp/releases
Keywords: genome bioinformatics sequence
Platform: Posix; MacOS X
Classifier: Development Status :: 4 - Beta
Classifier: Environment :: Console
Classifier: Intended Audience :: Science/Research
Classifier: License :: OSI Approved :: MIT License
Classifier: Natural Language :: English
Classifier: Operating System :: MacOS :: MacOS X
Classifier: Operating System :: POSIX :: Linux
Classifier: Programming Language :: Python
Classifier: Programming Language :: Python :: 3
Classifier: Programming Language :: Python :: 3.7
Classifier: Programming Language :: Python :: 3.8
Classifier: Topic :: Scientific/Engineering :: Bio-Informatics
Requires-Python: ~=3.5
Requires-Dist: biopython
Requires-Dist: bioservices
Requires-Dist: tqdm
